naima/__init__.py
naima/analysis.py
naima/core.py
naima/model_fitter.py
naima/model_utils.py
naima/models.py
naima/plot.py
naima/py.typed
naima/radiative.py
naima/setup_package.py
naima/sherpa_models.py
naima/utils.py
naima/version.py
naima/data/PionDecayKafexhiu14_LUT_NucEnh_Pythia8.npz
naima/data/tau_dominguez11.npz
naima/extern/__init__.py
naima/extern/minimize.py
naima/extern/validator.py
naima-0.10.3.dist-info/METADATA
naima-0.10.3.dist-info/WHEEL
naima-0.10.3.dist-info/licenses/LICENSE.rst
naima-0.10.3.dist-info/RECORD
