Metadata-Version: 2.4
Name: naima
Version: 0.10.3
Summary: Derivation of non-thermal particle distributions through MCMC spectral fitting
Author-email: Víctor Zabalza <vzabalza@gmail.com>
License-Expression: MIT
License-File: LICENSE.rst
Requires-Python: >=3.10
Requires-Dist: astropy>=6.1
Requires-Dist: corner>=2.0
Requires-Dist: emcee>=3.0
Requires-Dist: h5py>=3.14.0
Requires-Dist: matplotlib>=3.10.0
Requires-Dist: numpy>=2.0
Requires-Dist: pyyaml>=6.0.2
Requires-Dist: scipy>=1.15.3
